gepwc/__init__.py
gepwc/__version.py
gepwc/core.py
tst/test.py
gepwc-0.0.10855553854.dist-info/LICENSE
gepwc-0.0.10855553854.dist-info/METADATA
gepwc-0.0.10855553854.dist-info/WHEEL
gepwc-0.0.10855553854.dist-info/entry_points.txt
gepwc-0.0.10855553854.dist-info/top_level.txt
gepwc-0.0.10855553854.dist-info/RECORD
