Metadata-Version: 2.1
Name: gepwc
Version: 0.0.10855553854
Summary: This is a python version of wc, it perform serval common wc tasks
Author-email: Mouaad kadi <kadi.mouaad@gmail.com>
Maintainer-email: Mouaad kadi <kadi.mouaad@gmail.com>
License: MIT License
Project-URL: Repository, https://github.com/kadimouaad/gepwc
Keywords: wc,counting,words,chracters
License-File: LICENSE
Requires-Dist: click
Requires-Dist: importlib-metadata
